mxmul_pkg/__init__.py
mxmul_pkg/mxmul.py
mxmul_pkg_ZXW-0.1.0.dist-info/LICENSE
mxmul_pkg_ZXW-0.1.0.dist-info/METADATA
mxmul_pkg_ZXW-0.1.0.dist-info/WHEEL
mxmul_pkg_ZXW-0.1.0.dist-info/top_level.txt
mxmul_pkg_ZXW-0.1.0.dist-info/RECORD
