Metadata-Version: 2.1
Name: mxmul-pkg-ZXW
Version: 0.1.0
Summary: An example for teaching how to publish a Python package
Home-page: UNKNOWN
Author: Xiongwen Zheng
Author-email: 1213904351@qq.com
License: UNKNOWN
Platform: UNKNOWN
Classifier: Programming Language :: Python :: 3
Classifier: License :: OSI Approved :: MIT License
Classifier: Operating System :: OS Independent
